podhub.follower-0.0.211-py2.7-nspkg.pth
follower/__init__.py
follower/feed.py
follower/views.py
podhub/follower/__init__.py
podhub/follower/feed.py
podhub/follower/views.py
podhub.follower-0.0.211.data/scripts/follower
podhub.follower-0.0.211.dist-info/DESCRIPTION.rst
podhub.follower-0.0.211.dist-info/METADATA
podhub.follower-0.0.211.dist-info/metadata.json
podhub.follower-0.0.211.dist-info/namespace_packages.txt
podhub.follower-0.0.211.dist-info/RECORD
podhub.follower-0.0.211.dist-info/top_level.txt
podhub.follower-0.0.211.dist-info/WHEEL
